dynbsp/__init__.py
dynbsp/__main__.py
dynbsp/config.py
dynbsp/default_config.yaml
dynbsp/dynbsp.py
dynbsp/helpers.py
dynbsp/singleton.py
dynbsp/pybspc/__init__.py
dynbsp/pybspc/bspwm.py
dynbsp/pybspc/desktop.py
dynbsp/pybspc/monitor.py
dynbsp/pybspc/node.py
dynbsp/pybspc/subscription.py
dynbsp/pybspc/utils.py
dynbsp-1.0.3.dist-info/METADATA
dynbsp-1.0.3.dist-info/WHEEL
dynbsp-1.0.3.dist-info/entry_points.txt
dynbsp-1.0.3.dist-info/top_level.txt
dynbsp-1.0.3.dist-info/RECORD
