Metadata-Version: 2.1
Name: dynbsp
Version: 1.0.3
Summary: An application to dynamically add, remove and rename desktops from the BSP window manager
Home-page: https://github.com/j-waters/dynbsp
Author: James Waters
Author-email: james@jcwaters.co.uk
License: UNKNOWN
Platform: UNKNOWN
Requires-Python: >=3.8
Requires-Dist: Click
Requires-Dist: PyYAML
